Workbook

Sheet Priority & Sequence
A1: Seq # | B1: Priority | C1: Target Phase / Sprint | D1: Processor ID | E1: Step Processor Name | F1: Family Code | G1: Family Name | H1: Current Status | I1: Effort | J1: Assigned Owner / Team | K1: Target Release / Date | L1: Key Dependencies & Tech Seam | M1: Business Impact & Value
A2: 1 | B2: P0 | C2: Phase 1: Cloud & Lake | D2: SP-ACQ-06 | E2: AWS S3 object ingest | F2: ACQ | G2: Collectors & Ingestion | H2: Planned | I2: Med | L2: AWS SDK v2, `inspecto-connectors` | M2: Cloud file ingestion baseline; table stakes for AWS environments
A3: 2 | B3: P0 | C3: Phase 1: Cloud & Lake | D3: SP-ACQ-07 | E3: Azure Blob & ADLS Gen2 ingest | F3: ACQ | G3: Collectors & Ingestion | H3: Partial | I3: Low | L3: Azure Blob SDK, directory recursion test | M3: Quick win: verify ADLS Gen2 hierarchy on existing Azure connector
A4: 3 | B4: P0 | C4: Phase 1: Core Formats | D4: SP-PRS-05 | E4: XML / XPath / DOM unpacker | F4: PRS | G4: Extraction & Format Parsers | H4: Partial | I4: Med | L4: StAX / VTD-XML, `parser.xml` node | M4: Closes major enterprise ingestion gap beyond existing tree plugin
A5: 4 | B5: P0 | C5: Phase 1: Core Formats | D5: SP-PRS-14 | E5: Apache Avro binary decoder | F5: PRS | G5: Extraction & Format Parsers | H5: Planned | I5: Med | L5: DuckDB Avro scanner / Apache Avro | M5: High-speed ingestion for Kafka dumps and Hadoop migration feeds
A6: 5 | B6: P0 | C6: Phase 1: Core Formats | D6: SP-ACQ-05 | E6: Multi-sheet Excel workbook ingest | F6: ACQ | G6: Collectors & Ingestion | H6: Partial | I6: Low | L6: Apache POI / DuckDB Excel metadata | M6: Quick win: sheet discovery wrapper feeding existing `parser.xlsx`
A7: 6 | B7: P0 | C7: Phase 1: Advanced ETL | D7: SP-XFM-07 | E7: Dynamic pivot / transpose | F7: XFM | G7: Transformers & Dimensional Modeling | H7: Planned | I7: Low | L7: DuckDB `PIVOT` syntax lowerer | M7: Critical for financial, tabular, and time-matrix reporting
A8: 7 | B8: P0 | C8: Phase 1: Advanced ETL | D8: SP-XFM-08 | E8: Unpivot / column flattener | F8: XFM | G8: Transformers & Dimensional Modeling | H8: Planned | I8: Low | L8: DuckDB `UNPIVOT` syntax lowerer | M8: Normalizes wide survey/Excel tables into tidy relational rows
A9: 8 | B9: P0 | C9: Phase 1: Quality & Gov | D9: SP-DQ-06 | E9: Schema drift & new-field detector | F9: DQ | G9: Data Quality, Validation & Cleansing | H9: Partial | I9: Med | L9: Schema comparator, drift event bridge | M9: Prevents silent data corruption when upstream providers add fields
A10: 9 | B10: P0 | C10: Phase 1: Quality & Gov | D10: SP-SNK-15 | E10: Dead-letter queue (DLQ) | F10: SNK | G10: Sinks, Storage & Destinations | H10: Planned | I10: Med | L10: DLQ store layout, error payload wrapper | M10: Safe landing for poisoned records without failing batch jobs
A11: 10 | B11: P1 | C11: Phase 2: Streaming | D11: SP-ACQ-09 | E11: Apache Kafka consumer | F11: ACQ | G11: Collectors & Ingestion | H11: Partial | I11: Med | L11: Kafka consumer group, file buffer | M11: Connects event-driven Kafka topics into micro-batch pipelines
A12: 11 | B12: P1 | C12: Phase 2: Streaming | D12: SP-SNK-11 | E12: Apache Kafka topic producer | F12: SNK | G12: Sinks, Storage & Destinations | H12: Planned | I12: Med | L12: Kafka Producer client, JSON/Avro encoder | M12: Enables reverse-ETL streaming into downstream consumer buses
A13: 12 | B13: P1 | C13: Phase 2: Lakehouse | D13: SP-ACQ-15 | E13: Delta Lake table reader | F13: ACQ | G13: Collectors & Ingestion | H13: Planned | I13: High | L13: `delta-kernel-java` / DuckDB Delta ext | M13: Ingests versioned Delta tables directly from Databricks / S3
... A86: 85 | B86: N/A | C86: Maintain Legacy | D86: SP-SNK-04 | E86: Derived view | F86: SNK | G86: Sinks, Storage & Destinations | H86: Partial | I86: Low | L86: *Superseded by Datasets/Views* | M86: Grandfathered type maintained for backwards compatibility

Sheet All 119 Processors
A1: Board ID | B1: Catalog ID | C1: Emoji | D1: Processor Label | E1: Family Code | F1: Family Name | G1: Status | H1: Maps To | I1: Capability / Seam | J1: Addable in UI | K1: Notes & Gaps
A2: SP-ACQ-01 | B2: acquisition.file.local | C2: 📁 | D2: Local / NFS directory watcher | E2: ACQ | F2: Collectors & Ingestion | G2: Delivered | H2: acquisition | I2: — | J2: Yes | K2: LocalFileSystemConnector — the default collector
A3: SP-ACQ-02 | B3: acquisition.file.sftp | C3: 🔒 | D3: SFTP / FTPS remote ingest | E3: ACQ | F3: Collectors & Ingestion | G3: Delivered | H3: acquisition | I3: — | J3: Yes | K3: inspecto-connectors (sftp, ftps; key auth, bastion tunnel, host-key pinning)
A4: SP-ACQ-03 | B4: acquisition.db.jdbc | C4: 🗄️ | D4: JDBC / SQL query batch reader | E4: ACQ | F4: Collectors & Ingestion | G4: Delivered | H4: acquisition | I4: — | J4: Yes | K4: the db-export connector (`connector: db`, watermark column)
A5: SP-ACQ-04 | B5: acquisition.dataset | C5: 🧱 | D5: Dataset entry (re-ingest a registered Dataset) | E5: ACQ | F5: Collectors & Ingestion | G5: Delivered | H5: acquisition | I5: — | J5: Yes | K5: UI-S7: `connector: dataset` + `on:dataset` trigger
A6: SP-ACQ-05 | B6: acquisition.file.excel | C6: 📑 | D6: Multi-sheet Excel workbook ingest | E6: ACQ | F6: Collectors & Ingestion | G6: Partial | H6: parser.xlsx | I6: — | J6: Yes | K6: the xlsx PARSER is delivered; per-sheet workbook fan-out as an acquisition is not
A7: SP-ACQ-06 | B7: acquisition.file.s3 | C7: ☁️ | D7: AWS S3 object ingest | E7: ACQ | F7: Collectors & Ingestion | G7: Planned | H7: — | I7: — | J7: No
A8: SP-ACQ-07 | B8: acquisition.file.azure | C8: 🌐 | D8: Azure Blob & ADLS Gen2 ingest | E8: ACQ | F8: Collectors & Ingestion | G8: Partial | H8: acquisition | I8: — | J8: Yes | K8: Connection kind exists (azure blob connector); ADLS Gen2 semantics not proven
A9: SP-ACQ-08 | B9: acquisition.file.gcs | C9: 🪣 | D9: Google Cloud Storage ingest | E9: ACQ | F9: Collectors & Ingestion | G9: Planned | H9: — | I9: — | J9: No
A10: SP-ACQ-09 | B10: acquisition.stream.kafka | C10: 📤 | D10: Apache Kafka consumer | E10: ACQ | F10: Collectors & Ingestion | G10: Partial | H10: acquisition | I10: — | J10: Yes | K10: Connection kind exists (kafka); consumer-group ingest as a Collector not proven
A11: SP-ACQ-10 | B11: acquisition.stream.pulsar | C11: 📨 | D11: Apache Pulsar consumer | E11: ACQ | F11: Collectors & Ingestion | G11: Planned | H11: — | I11: — | J11: No
A12: SP-ACQ-11 | B12: acquisition.stream.kinesis | C12: 📬 | D12: AWS Kinesis / SQS ingest | E12: ACQ | F12: Collectors & Ingestion | G12: Planned | H12: — | I12: — | J12: No
A13: SP-ACQ-12 | B13: acquisition.stream.rabbitmq | C13: 🐰 | D13: RabbitMQ AMQP subscriber | E13: ACQ | F13: Collectors & Ingestion | G13: Planned | H13: — | I13: — | J13: No
A14: SP-ACQ-13 | B14: acquisition.stream.mqtt | C14: 📡 | D14: MQTT IoT telemetry ingest | E14: ACQ | F14: Collectors & Ingestion | G14: Planned | H14: — | I14: — | J14: No
A15: SP-ACQ-14 | B15: acquisition.cdc.debezium | C15: 🔄 | D15: Change Data Capture (Debezium) | E15: ACQ | F15: Collectors & Ingestion | G15: Planned | H15: — | I15: — | J15: No
A16: SP-ACQ-15 | B16: acquisition.lake.delta | C16: 💾 | D16: Delta Lake table reader | E16: ACQ | F16: Collectors & Ingestion | G16: Planned | H16: — | I16: — | J16: No
A17: SP-ACQ-16 | B17: acquisition.lake.iceberg | C17: 🧊 | D17: Apache Iceberg table ingest | E17: ACQ | F17: Collectors & Ingestion | G17: Planned | H17: — | I17: — | J17: No
A18: SP-ACQ-17 | B18: acquisition.db.cloud | C18: ❄️ | D18: Snowflake / BigQuery ingest | E18: ACQ | F18: Collectors & Ingestion | G18: Planned | H18: — | I18: — | J18: No
A19: SP-ACQ-18 | B19: acquisition.api.rest | C19: 🌐 | D19: REST API poller & paged ingest | E19: ACQ | F19: Collectors & Ingestion | G19: Planned | H19: — | I19: — | J19: No
A20: SP-ACQ-19 | B20: acquisition.api.webhook | C20: 🪝 | D20: HTTP webhook listener endpoint | E20: ACQ | F20: Collectors & Ingestion | G20: Planned | H20: — | I20: — | J20: No
A21: SP-ACQ-20 | B21: acquisition.api.grpc | C21: 🔌 | D21: gRPC stream receiver | E21: ACQ | F21: Collectors & Ingestion | G21: Planned | H21: — | I21: — | J21: No
A22: SP-PRS-01 | B22: parser.delimited | C22: 📄 | D22: Delimited / CSV / TSV / PSV parser | E22: PRS | F22: Extraction & Format Parsers | G22: Delivered | H22: parser.delimited | I22: — | J22: Yes
A23: SP-PRS-02 | B23: parser.fixedwidth | C23: 📦 | D23: Fixed-width column slicer | E23: PRS | F23: Extraction & Format Parsers | G23: Delivered | H23: parser.fixedwidth | I23: — | J23: Yes | K23: text (`record: line`) and fixed-length binary (`record: bytes`)
A24: SP-PRS-03 | B24: parser.json | C24: 🧬 | D24: JSON object & JSON Lines (NDJSON) parser | E24: PRS | F24: Extraction & Format Parsers | G24: Delivered | H24: parser.json | I24: — | J24: Yes
A25: SP-PRS-04 | B25: parser.excel | C25: 📑 | D25: Excel workbook parser | E25: PRS | F25: Extraction & Format Parsers | G25: Delivered | H25: parser.xlsx | I25: — | J25: Yes | K25: needs the DuckDB `excel` extension in the bundle (multiformat X1)
A26: SP-PRS-05 | B26: parser.xml | C26: 📑 | D26: XML / XPath / DOM unpacker | E26: PRS | F26: Extraction & Format Parsers | G26: Partial | H26: parser.plugin | I26: — | J26: Yes | K26: tree→segments bridge ships XML ingests; no XPath selector grammar yet
A27: SP-PRS-06 | B27: parser.asn1.ber | C27: 📡 | D27: ASN.1 BER telecom CDR decoder | E27: PRS | F27: Extraction & Format Parsers | G27: Delivered | H27: — | I27: parser.asn1 | J27: No | K27: asn-parser reactor (decoders, vendor plugins)
A28: SP-PRS-07 | B28: parser.pattern.regex | C28: 🔎 | D28: Named-group regex extractor | E28: PRS | F28: Extraction & Format Parsers | G28: Delivered | H28: parser.text_regex | I28: — | J28: Yes
A29: SP-PRS-08 | B29: parser.plugin | C29: 🧩 | D29: Custom ingester plugin (segments, multi-event) | E29: PRS | F29: Extraction & Format Parsers | G29: Delivered | H29: parser.plugin | I29: — | J29: Yes | K29: ParserPlugin SPI; `segments: {CALL, SMS}`
A30: SP-PRS-09 | B30: parser.keyvalue | C30: 🏷️ | D30: Key-value / logfmt parser | E30: PRS | F30: Extraction & Format Parsers | G30: Planned | H30: — | I30: — | J30: No
A31: SP-PRS-10 | B31: parser.yaml | C31: 📜 | D31: YAML document slicer | E31: PRS | F31: Extraction & Format Parsers | G31: Planned | H31: — | I31: — | J31: No
A32: SP-PRS-11 | B32: parser.asn1.per | C32: 📜 | D32: ASN.1 PER / XER / DER decoder | E32: PRS | F32: Extraction & Format Parsers | G32: Planned | H32: — | I32: — | J32: No
A33: SP-PRS-12 | B33: parser.mainframe.ebcdic | C33: 📠 | D33: Mainframe EBCDIC & COBOL copybook | E33: PRS | F33: Extraction & Format Parsers | G33: Planned | H33: — | I33: — | J33: No
A34: SP-PRS-13 | B34: parser.binary.protobuf | C34: ⚡ | D34: Protocol Buffers decoder | E34: PRS | F34: Extraction & Format Parsers | G34: Planned | H34: — | I34: — | J34: No
A35: SP-PRS-14 | B35: parser.binary.avro | C35: 🦅 | D35: Apache Avro binary decoder | E35: PRS | F35: Extraction & Format Parsers | G35: Planned | H35: — | I35: — | J35: No
A36: SP-PRS-15 | B36: parser.binary.pcap | C36: 🌐 | D36: PCAP network packet slicer | E36: PRS | F36: Extraction & Format Parsers | G36: Planned | H36: — | I36: — | J36: No
A37: SP-PRS-16 | B37: parser.pattern.grok | C37: 📜 | D37: Grok / Logstash expression matcher | E37: PRS | F37: Extraction & Format Parsers | G37: Planned | H37: — | I37: — | J37: No
A38: SP-PRS-17 | B38: parser.pattern.syslog | C38: 🖥️ | D38: Syslog RFC 5424 / RFC 3164 parser | E38: PRS | F38: Extraction & Format Parsers | G38: Planned | H38: — | I38: — | J38: No
A39: SP-DQ-01 | B39: quality.schema.validator | C39: 🛡️ | D39: Schema registry & structural rejects | E39: DQ | F39: Data Quality, Validation & Cleansing | G39: Delivered | H39: parser | I39: — | J39: No | K39: the declared schema on the Parse Step: typed fields, TRY_CAST at ingest, structural rejects → quarantine. ⛔ Only HALF of the old "Schema validator & type coercion" — coercion as an AUTHORING act folded into `transform.record` (2026-09-04). What cannot fold is the schema CONTRACT: the declared source column + target type are the cast-failure audit's denominator, and `SchemaCompatibility` gates edits to them BACKWARD
A40: SP-DQ-02 | B40: quality.constraint.check | C40: ⚠️ | D40: Constraint & range checker (Expectations) | E40: DQ | F40: Data Quality, Validation & Cleansing | G40: Delivered | H40: — | I40: expectation | J40: No | K40: Expectations evaluated per Dataset (`ExpectationEvaluator`); not a mid-chain step
A41: SP-DQ-03 | B41: quality.dedup.exact | C41: 🧼 | D41: Exact-key deduplicator (within a Consignment) | E41: DQ | F41: Data Quality, Validation & Cleansing | G41: Delivered | H41: transform.dedup | I41: — | J41: Yes | K41: `scope: consignment` (default)
A42: SP-DQ-04 | B42: quality.dedup.windowed | C42: ⏱️ | D42: Sliding time-window deduplicator | E42: DQ | F42: Data Quality, Validation & Cleansing | G42: Delivered | H42: transform.dedup | I42: — | J42: Yes | K42: D-9: `scope: window(P4D)` + the durable dedup ledger
A43: SP-DQ-05 | B43: quality.dedup.file | C43: 🗂️ | D43: File-grain duplicate guard (path / checksum / metadata / marker) | E43: DQ | F43: Data Quality, Validation & Cleansing | G43: Delivered | H43: acquisition | I43: — | J43: Yes | K43: Collector `duplicate:` policy + marker dedup — a Guarantee, rides the Collector
A44: SP-DQ-06 | B44: quality.schema.drift | C44: 🧬 | D44: Schema drift & new-field detector | E44: DQ | F44: Data Quality, Validation & Cleansing | G44: Partial | H44: — | I44: expectation | J44: No | K44: multi-schema dispatch refuses unknown shapes; no drift REPORT yet
A45: SP-DQ-07 | B45: quality.cluster.edit | C45: 🔍 | D45: Cluster & edit value normalizer | E45: DQ | F45: Data Quality, Validation & Cleansing | G45: Planned | H45: — | I45: — | J45: No
A46: SP-DQ-08 | B46: quality.match.fuzzy | C46: 🔍 | D46: Fuzzy string (Jaro-Winkler) matcher | E46: DQ | F46: Data Quality, Validation & Cleansing | G46: Planned | H46: — | I46: — | J46: No
A47: SP-DQ-09 | B47: quality.profiler.inline | C47: 🧮 | D47: Inline stream profiler & statistics | E47: DQ | F47: Data Quality, Validation & Cleansing | G47: Partial | H47: — | I47: storage_report | J47: No | K47: storage/completeness KPIs exist; no per-column profile step
A48: SP-DQ-10 | B48: quality.sample.reservoir | C48: 📊 | D48: Statistical & reservoir sampler | E48: DQ | F48: Data Quality, Validation & Cleansing | G48: Planned | H48: — | I48: — | J48: No
A49: SP-DQ-11 | B49: quality.cleanse.transcode | C49: 🔤 | D49: Character map & code page transcoder | E49: DQ | F49: Data Quality, Validation & Cleansing | G49: Planned | H49: — | I49: — | J49: No
A50: SP-DQ-12 | B50: quality.pii.mask | C50: 🔒 | D50: PII masking & tokenization | E50: DQ | F50: Data Quality, Validation & Cleansing | G50: Planned | H50: — | I50: — | J50: No | K50: board SEC-08 — Enterprise only
A51: SP-DQ-13 | B51: quality.crypto.hash | C51: 🔑 | D51: One-way salted cryptographic hasher | E51: DQ | F51: Data Quality, Validation & Cleansing | G51: Planned | H51: — | I51: — | J51: No
A52: SP-DQ-14 | B52: quality.compliance.redact | C52: 🛡️ | D52: GDPR / CCPA field redactor | E52: DQ | F52: Data Quality, Validation & Cleansing | G52: Planned | H52: — | I52: — | J52: No | K52: board SEC-08 — Enterprise only
A53: SP-XFM-01 | B53: transform.record | C53: 🧮 | D53: Record Transformer | E53: XFM | F53: Transformers & Dimensional Modeling | G53: Delivered | H53: transform.sql | I53: — | J53: Yes | K53: ONE Step that shapes a record: sanitize (trim/pad/replace/case), cast, rename and computed columns — one row per output field over a typed function catalog, generating the SELECT it saves. Folded 2026-09-04 from `transform.expression` + `transform.cast` + `quality.cleanse.trim`, which were three catalog labels over this one grid. `transform.map` was deleted 2026-09-05: a stored `mapping.rules[]` is read as `fields[]` (EXPR → custom, CONCAT_DT → date.concat_parts, FILENAME_DATE → date.from_filename)
A54: SP-XFM-02 | B54: transform.filter | C54: 🔽 | D54: Row filter (pre-parse regex / post-map predicate) | E54: XFM | F54: Transformers & Dimensional Modeling | G54: Delivered | H54: transform.filter | I54: — | J54: Yes
A55: SP-XFM-03 | B55: transform.route | C55: 🔀 | D55: Router — case / clone branches with mid-branch steps | E55: XFM | F55: Transformers & Dimensional Modeling | G55: Delivered | H55: transform.route | I55: — | J55: Yes
A56: SP-XFM-04 | B56: transform.summarize | C56: ∑ | D56: Group-by summarizer (measures grammar) | E56: XFM | F56: Transformers & Dimensional Modeling | G56: Delivered | H56: transform.summarize | I56: — | J56: Yes
A57: SP-XFM-05 | B57: transform.join | C57: 🤝 | D57: Reference-store join (versioned references) | E57: XFM | F57: Transformers & Dimensional Modeling | G57: Delivered | H57: transform.join | I57: — | J57: Yes | K57: at rest only — refused mid-branch (no reference resolver on the ingest lane)
A58: SP-XFM-06 | B58: transform.lookup | C58: 🗺️ | D58: Lookup & static map transcoder | E58: XFM | F58: Transformers & Dimensional Modeling | G58: Delivered | H58: transform.lookup | I58: — | J58: Yes | K58: inline key=value map over one column (2026-09-06); a versioned reference is transform.join
A59: SP-XFM-07 | B59: transform.matrix.pivot | C59: 🔀 | D59: Dynamic pivot / transpose | E59: XFM | F59: Transformers & Dimensional Modeling | G59: Planned | H59: — | I59: — | J59: No
A60: SP-XFM-08 | B60: transform.matrix.unpivot | C60: 🔄 | D60: Unpivot / column flattener | E60: XFM | F60: Transformers & Dimensional Modeling | G60: Planned | H60: — | I60: — | J60: No
A61: SP-XFM-09 | B61: transform.analytics.rank | C61: 🏆 | D61: Rank & Top-N pruner | E61: XFM | F61: Transformers & Dimensional Modeling | G61: Planned | H61: — | I61: — | J61: No
A62: SP-XFM-10 | B62: transform.explode | C62: 💥 | D62: Array / object exploder & flattener | E62: XFM | F62: Transformers & Dimensional Modeling | G62: Planned | H62: — | I62: — | J62: No | K62: the grandfathered `transform.split` node type is the read-only ancestor
A63: SP-XFM-11 | B63: transform.join.merge | C63: 🤝 | D63: Presorted stream merge joiner | E63: XFM | F63: Transformers & Dimensional Modeling | G63: Planned | H63: — | I63: — | J63: No | K63: the grandfathered `transform.merge` node type is the read-only ancestor
A64: SP-XFM-12 | B64: transform.dim.scd2 | C64: 🏛️ | D64: Slowly changing dimension (SCD Type 2) | E64: XFM | F64: Transformers & Dimensional Modeling | G64: Planned | H64: — | I64: — | J64: No
A65: SP-XFM-13 | B65: transform.key.surrogate | C65: 🔑 | D65: Monotonic surrogate key generator | E65: XFM | F65: Transformers & Dimensional Modeling | G65: Planned | H65: — | I65: — | J65: No
A66: SP-XFM-14 | B66: transform.dml.strategy | C66: 🏷️ | D66: DML row-action strategy flagger | E66: XFM | F66: Transformers & Dimensional Modeling | G66: Planned | H66: — | I66: — | J66: No
A67: SP-XFM-15 | B67: transform.diff.compare | C67: ⚖️ | D67: Dataset differ & change compare | E67: XFM | F67: Transformers & Dimensional Modeling | G67: Partial | H67: — | I67: recon | J67: No | K67: Reconciliation boards compare Datasets; not a chain step
A68: SP-XFM-16 | B68: transform.builder.xml | C68: 🏗️ | D68: Hierarchical XML / JSON document builder | E68: XFM | F68: Transformers & Dimensional Modeling | G68: Planned | H68: — | I68: — | J68: No
A69: SP-XFM-17 | B69: transform.fintech.ifrs | C69: 📊 | D69: IFRS 15 / IFRS 9 revenue recognition engine | E69: XFM | F69: Transformers & Dimensional Modeling | G69: Planned | H69: — | I69: — | J69: No
A70: SP-XFM-18 | B70: transform.telecom.simbox | C70: 📱 | D70: SIM box & bypass fraud detector | E70: XFM | F70: Transformers & Dimensional Modeling | G70: Planned | H70: — | I70: — | J70: No
A71: SP-XFM-19 | B71: transform.telecom.rating | C71: 💵 | D71: Tariff, rating & usage billing engine | E71: XFM | F71: Transformers & Dimensional Modeling | G71: Planned | H71: — | I71: — | J71: No
A72: SP-XFM-20 | B72: transform.telecom.roaming | C72: 🌍 | D72: Roaming TAP3 / CIBER surcharger | E72: XFM | F72: Transformers & Dimensional Modeling | G72: Planned | H72: — | I72: — | J72: No
A73: SP-XFM-21 | B73: transform.fintech.velocity | C73: 🚨 | D73: Velocity & impossible-travel anomaly | E73: XFM | F73: Transformers & Dimensional Modeling | G73: Planned | H73: — | I73: — | J73: No
A74: SP-BI-01 | B74: transform.analytics.lod | C74: 🏛️ | D74: Level-of-detail (LOD) fixed aggregator | E74: BI | F74: Analytics, Time-Series & Semantic Modeling | G74: Planned | H74: — | I74: — | J74: No
A75: SP-BI-02 | B75: transform.analytics.lod_context | C75: 🏛️ | D75: LOD include / exclude context aggregator | E75: BI | F75: Analytics, Time-Series & Semantic Modeling | G75: Planned | H75: — | I75: — | J75: No
A76: SP-BI-03 | B76: transform.timeseries.resample | C76: ⏱️ | D76: Time-grain resampler & gap imputer | E76: BI | F76: Analytics, Time-Series & Semantic Modeling | G76: Partial | H76: — | I76: measure-grammar | J76: No | K76: time grains exist in Studio queries (`QuerySpec.grains`); no resampling step
A77: SP-BI-04 | B77: transform.timeseries.shift | C77: 📈 | D77: Period-over-period (YoY / MoM / WoW) shift | E77: BI | F77: Analytics, Time-Series & Semantic Modeling | G77: Planned | H77: — | I77: — | J77: No
A78: SP-BI-05 | B78: transform.analytics.running | C78: 📊 | D78: Running calculations & moving averages | E78: BI | F78: Analytics, Time-Series & Semantic Modeling | G78: Planned | H78: — | I78: — | J78: No
A79: SP-BI-06 | B79: transform.timeseries.forecast | C79: 🔮 | D79: Time-series forecaster (Holt-Winters) | E79: BI | F79: Analytics, Time-Series & Semantic Modeling | G79: Planned | H79: — | I79: — | J79: No
A80: SP-BI-07 | B80: transform.semantic.metric | C80: 📐 | D80: Semantic KPI calculator & Measure formulas | E80: BI | F80: Analytics, Time-Series & Semantic Modeling | G80: Partial | H80: — | I80: measure-grammar | J80: No | K80: the Measure grammar (`count | agg(field)`) serves Studio + summarize; no named-KPI layer
A81: SP-BI-08 | B81: transform.param.jinja | C81: 🏷️ | D81: Template & runtime parameter injector | E81: BI | F81: Analytics, Time-Series & Semantic Modeling | G81: Partial | H81: — | I81: sql.template | J81: No | K81: the `sql.template` job resolves `$name` tokens; no Jinja
A82: SP-BI-09 | B82: transform.data.binning | C82: 📦 | D82: Histogram & quantile binner | E82: BI | F82: Analytics, Time-Series & Semantic Modeling | G82: Planned | H82: — | I82: — | J82: No
A83: SP-BI-10 | B83: transform.string.smart_split | C83: ✂️ | D83: Smart custom string splitter | E83: BI | F83: Analytics, Time-Series & Semantic Modeling | G83: Planned | H83: — | I83: — | J83: No
A84: SP-BI-11 | B84: transform.geo.h3 | C84: 🗺️ | D84: H3 hexagonal & geohash grid indexer | E84: BI | F84: Analytics, Time-Series & Semantic Modeling | G84: Planned | H84: — | I84: — | J84: No | K84: needs the DuckDB `spatial`/`h3` extension — board CP-09 gate
A85: SP-BI-12 | B85: transform.geo.spatial_join | C85: 📍 | D85: Spatial polygon & point-in-polygon intersect | E85: BI | F85: Analytics, Time-Series & Semantic Modeling | G85: Planned | H85: — | I85: — | J85: No | K85: needs the DuckDB `spatial` extension — deliberately not loaded (SqlSandbox)
A86: SP-BI-13 | B86: transform.stats.outlier | C86: 🚨 | D86: Outlier detector & IQR boxplot fencer | E86: BI | F86: Analytics, Time-Series & Semantic Modeling | G86: Planned | H86: — | I86: — | J86: No
A87: SP-BI-14 | B87: transform.stats.correlation | C87: 🧮 | D87: Pearson & Spearman correlation matrix | E87: BI | F87: Analytics, Time-Series & Semantic Modeling | G87: Planned | H87: — | I87: — | J87: No
A88: SP-ENR-01 | B88: enrichment.reference | C88: 📚 | D88: Reference-table enrichment (`*_enrich.toon`, Stage-2) | E88: ENR | F88: Enrichment, Entity Resolution & AI/ML | G88: Delivered | H88: enrichment | I88: — | J88: Yes | K88: the shipped enrichment job + versioned references
A89: SP-ENR-02 | B89: enrichment.geoip | C89: 🌍 | D89: GeoIP & ISP geolocation enricher | E89: ENR | F89: Enrichment, Entity Resolution & AI/ML | G89: Planned | H89: — | I89: — | J89: No
A90: SP-ENR-03 | B90: enrichment.redis | C90: ⚡ | D90: Redis / in-memory cache lookup | E90: ENR | F90: Enrichment, Entity Resolution & AI/ML | G90: Planned | H90: — | I90: — | J90: No
A91: SP-ENR-04 | B91: enrichment.rest | C91: 🌐 | D91: Dynamic microservice REST enricher | E91: ENR | F91: Enrichment, Entity Resolution & AI/ML | G91: Planned | H91: — | I91: — | J91: No
A92: SP-ENR-05 | B92: transform.db.procedure | C92: 🗄️ | D92: Parameterized stored-procedure caller | E92: ENR | F92: Enrichment, Entity Resolution & AI/ML | G92: Planned | H92: — | I92: — | J92: No
A93: SP-ENR-06 | B93: enrichment.entity.link | C93: 🔗 | D93: Master entity resolution & record linkage | E93: ENR | F93: Enrichment, Entity Resolution & AI/ML | G93: Planned | H93: — | I93: — | J93: No
A94: SP-ENR-07 | B94: enrichment.graph.cluster | C94: 🕸️ | D94: Graph cluster & connected-component tagger | E94: ENR | F94: Enrichment, Entity Resolution & AI/ML | G94: Partial | H94: — | I94: link-analysis | J94: No | K94: link-analysis VIEW ships (projection); no tagging step
A95: SP-ENR-08 | B95: ml.inference.onnx | C95: 🤖 | D95: ONNX Runtime embedded inference | E95: ENR | F95: Enrichment, Entity Resolution & AI/ML | G95: Planned | H95: — | I95: — | J95: No | K95: the optional `inspecto-intelligence` module carries onnxruntime; never bundled
A96: SP-ENR-09 | B96: ml.llm.classify | C96: 🏷️ | D96: LLM zero-shot classifier & tagging | E96: ENR | F96: Enrichment, Entity Resolution & AI/ML | G96: Planned | H96: — | I96: — | J96: No | K96: assist/intelligence agents are never bundled (CP-14)
A97: SP-ENR-10 | B97: ml.embedding.vector | C97: 📐 | D97: Text embeddings & vector generator | E97: ENR | F97: Enrichment, Entity Resolution & AI/ML | G97: Planned | H97: — | I97: — | J97: No
A98: SP-CTL-01 | B98: control.file.sequence_analyzer | C98: 🕳️ | D98: File sequence & gap integrity analyzer | E98: CTL | F98: Control, Governance & Sequence Integrity | G98: Delivered | H98: gap | I98: — | J98: Yes | K98: Collector `gap_detection: {sequence}` → the gap node + SEQUENCE_GAP events
A99: SP-CTL-02 | B99: control.gap.detector | C99: 🕳️ | D99: Sequence-gap & data-loss watchdog | E99: CTL | F99: Control, Governance & Sequence Integrity | G99: Delivered | H99: gap | I99: — | J99: Yes | K99: same detector; gaps raise ALERT objects via the EventObjectBridge
A100: SP-CTL-03 | B100: control.audit.stamp | C100: 🏷️ | D100: Audit metadata & lineage stamper | E100: CTL | F100: Control, Governance & Sequence Integrity | G100: Delivered | H100: sink.persistent | I100: — | J100: Yes | K100: `filename_column` + the per-file/batch/lineage ledgers + `__batch_id` provenance
...

Sheet Dashboard & KPIs
A1: Inspecto Step Processors Portfolio Dashboard
A3: Portfolio Status Summary (All 119 Processors)
A4: Family Code | B4: Family Label | C4: Delivered (✅) | D4: Partial (🟡) | E4: Planned (🔲) | F4: Total Processors | G4: % Delivered
A5: ACQ | B5: Collectors & Ingestion | C5: =COUNTIFS('All 119 Processors'!$E:$E, A5, 'All 119 Processors'!$G:$G, "Delivered") | D5: =COUNTIFS('All 119 Processors'!$E:$E, A5, 'All 119 Processors'!$G:$G, "Partial") | E5: =COUNTIFS('All 119 Processors'!$E:$E, A5, 'All 119 Processors'!$G:$G, "Planned") | F5: =SUM(C5:E5) | G5: =C5/F5
A6: PRS | B6: Extraction & Format Parsers | C6: =COUNTIFS('All 119 Processors'!$E:$E, A6, 'All 119 Processors'!$G:$G, "Delivered") | D6: =COUNTIFS('All 119 Processors'!$E:$E, A6, 'All 119 Processors'!$G:$G, "Partial") | E6: =COUNTIFS('All 119 Processors'!$E:$E, A6, 'All 119 Processors'!$G:$G, "Planned") | F6: =SUM(C6:E6) | G6: =C6/F6
A7: DQ | B7: Data Quality, Validation & Cleansing | C7: =COUNTIFS('All 119 Processors'!$E:$E, A7, 'All 119 Processors'!$G:$G, "Delivered") | D7: =COUNTIFS('All 119 Processors'!$E:$E, A7, 'All 119 Processors'!$G:$G, "Partial") | E7: =COUNTIFS('All 119 Processors'!$E:$E, A7, 'All 119 Processors'!$G:$G, "Planned") | F7: =SUM(C7:E7) | G7: =C7/F7
A8: XFM | B8: Transformers & Dimensional Modeling | C8: =COUNTIFS('All 119 Processors'!$E:$E, A8, 'All 119 Processors'!$G:$G, "Delivered") | D8: =COUNTIFS('All 119 Processors'!$E:$E, A8, 'All 119 Processors'!$G:$G, "Partial") | E8: =COUNTIFS('All 119 Processors'!$E:$E, A8, 'All 119 Processors'!$G:$G, "Planned") | F8: =SUM(C8:E8) | G8: =C8/F8
A9: BI | B9: Analytics, Time-Series & Semantic Modeling | C9: =COUNTIFS('All 119 Processors'!$E:$E, A9, 'All 119 Processors'!$G:$G, "Delivered") | D9: =COUNTIFS('All 119 Processors'!$E:$E, A9, 'All 119 Processors'!$G:$G, "Partial") | E9: =COUNTIFS('All 119 Processors'!$E:$E, A9, 'All 119 Processors'!$G:$G, "Planned") | F9: =SUM(C9:E9) | G9: =C9/F9
A10: ENR | B10: Enrichment, Entity Resolution & AI/ML | C10: =COUNTIFS('All 119 Processors'!$E:$E, A10, 'All 119 Processors'!$G:$G, "Delivered") | D10: =COUNTIFS('All 119 Processors'!$E:$E, A10, 'All 119 Processors'!$G:$G, "Partial") | E10: =COUNTIFS('All 119 Processors'!$E:$E, A10, 'All 119 Processors'!$G:$G, "Planned") | F10: =SUM(C10:E10) | G10: =C10/F10
A11: CTL | B11: Control, Governance & Sequence Integrity | C11: =COUNTIFS('All 119 Processors'!$E:$E, A11, 'All 119 Processors'!$G:$G, "Delivered") | D11: =COUNTIFS('All 119 Processors'!$E:$E, A11, 'All 119 Processors'!$G:$G, "Partial") | E11: =COUNTIFS('All 119 Processors'!$E:$E, A11, 'All 119 Processors'!$G:$G, "Planned") | F11: =SUM(C11:E11) | G11: =C11/F11
A12: SNK | B12: Sinks, Storage & Destinations | C12: =COUNTIFS('All 119 Processors'!$E:$E, A12, 'All 119 Processors'!$G:$G, "Delivered") | D12: =COUNTIFS('All 119 Processors'!$E:$E, A12, 'All 119 Processors'!$G:$G, "Partial") | E12: =COUNTIFS('All 119 Processors'!$E:$E, A12, 'All 119 Processors'!$G:$G, "Planned") | F12: =SUM(C12:E12) | G12: =C12/F12
A13: TOTAL | B13: All 8 Families | C13: =SUM(C5:C12) | D13: =SUM(D5:D12) | E13: =SUM(E5:E12) | F13: =SUM(F5:F12) | G13: =C13/F13
A16: Pending Processors Priority Distribution (Sheet: Priority & Sequence)
A17: Priority Tier | B17: Definition | C17: Count | D17: % of Pending Backlog
A18: P0 | B18: Critical / Immediate (Phase 1 Baseline & Quick Wins) | C18: =COUNTIF('Priority & Sequence'!$B:$B, A18) | D18: =C18/SUM($C$18:$C$22)
A19: P1 | B19: High Value (Lakehouse, Streaming, Modeling, Security) | C19: =COUNTIF('Priority & Sequence'!$B:$B, A19) | D19: =C19/SUM($C$18:$C$22)
A20: P2 | B20: Medium Value (Multi-Cloud, Advanced Analytics, Quality) | C20: =COUNTIF('Priority & Sequence'!$B:$B, A20) | D20: =C20/SUM($C$18:$C$22)
A21: P3 | B21: Specialized / Niche (Telecom, FinTech, Legacy, AI/ML) | C21: =COUNTIF('Priority & Sequence'!$B:$B, A21) | D21: =C21/SUM($C$18:$C$22)
A22: N/A | B22: Internal Engine Core or Superseded Capabilities | C22: =COUNTIF('Priority & Sequence'!$B:$B, A22) | D22: =C22/SUM($C$18:$C$22)
A23: TOTAL | B23: Total Pending Backlog | C23: =SUM(C18:C22) | D23: 100.0%
